arrendatools/__init__.py
arrendatools/modelo303/__init__.py
arrendatools/modelo303/datos.py
arrendatools/modelo303/factory.py
arrendatools/modelo303/generador.py
arrendatools/modelo303/generadores/__init__.py
arrendatools/modelo303/generadores/generador_ejercicio_2023.py
arrendatools/modelo303/generadores/generador_ejercicio_2024.py
arrendatools/modelo303/generadores/generador_ejercicio_2025.py
arrendatools.modelo303-2026.1.0.dist-info/LICENSE
arrendatools.modelo303-2026.1.0.dist-info/METADATA
arrendatools.modelo303-2026.1.0.dist-info/WHEEL
arrendatools.modelo303-2026.1.0.dist-info/top_level.txt
arrendatools.modelo303-2026.1.0.dist-info/RECORD
