Metadata-Version: 2.2
Name: arrendatools.modelo303
Version: 2026.1.0
Summary: Módulo de Python que genera un string para la importación de datos en el modelo 303 de la Agencia Tributaria de España (PRE 303 - Servicio ayuda modelo 303).
Author-email: Jordi Morell <hokus@hotmail.com>
License: MIT
Classifier: Development Status :: 4 - Beta
Classifier: Intended Audience :: Developers
Classifier: License :: OSI Approved :: MIT License
Classifier: Programming Language :: Python :: 3.10
Classifier: Programming Language :: Python :: 3.11
Classifier: Programming Language :: Python :: 3.12
Requires-Python: >=3.10
License-File: LICENSE
